nextpay/__init__.py
nextpay/exceptions.py
nextpay/nextpay.py
nextpay-1.0.0.dist-info/LICENSE
nextpay-1.0.0.dist-info/METADATA
nextpay-1.0.0.dist-info/WHEEL
nextpay-1.0.0.dist-info/top_level.txt
nextpay-1.0.0.dist-info/RECORD
