Metadata-Version: 2.1
Name: nextpay
Version: 1.0.0
Summary: A library for requesting to the nextpay.org purchase gate way.
Author-email: Hadi Alipoor <hadi.alipoor.h2o@gmail.com>
License: MIT License        
Project-URL: Homepage, https://github.com/HadiH2o/NextPay
Project-URL: Bug Tracker, https://github.com/HadiH2o/NextPay/issues
Classifier: Programming Language :: Python :: 3
Classifier: License :: OSI Approved :: MIT License
Classifier: Operating System :: OS Independent
Requires-Python: >=3.7
License-File: LICENSE
Requires-Dist: requests (==2.28.1)
